mimap/__init__.py
mimap/_dump_code.py
mimap/block.py
mimap/highlevel.py
mimap/item.py
mimap/priority.py
mimap-0.3.1.dist-info/LICENSE
mimap-0.3.1.dist-info/METADATA
mimap-0.3.1.dist-info/WHEEL
mimap-0.3.1.dist-info/top_level.txt
mimap-0.3.1.dist-info/RECORD
