Metadata-Version: 2.1
Name: mimap
Version: 0.3.1
Summary: Associates python object with priority.
Home-page: https://github.com/sekgobela-kevin/mimap
Author: Sekgobela Kevin
Author-email: kevinnoko23@gmail.com
Project-URL: Bug Tracker, https://github.com/sekgobela-kevin/mimap/issues
Keywords: mapping,associate,priority,object,item,block
Classifier: Intended Audience :: Developers
Classifier: Development Status :: 2 - Pre-Alpha
Classifier: Programming Language :: Python
Classifier: Programming Language :: Python :: 3
Classifier: Topic :: Software Development :: Libraries
Classifier: Topic :: Software Development :: Libraries :: Python Modules
Classifier: Topic :: Utilities
Requires-Python: >=3.6
License-File: LICENSE
Requires-Dist: pemap (<0.2.0,>=0.1.1)
